touml-0.1.4.dist-info/METADATA
touml-0.1.4.dist-info/WHEEL
touml-0.1.4.dist-info/licenses/LICENSE
touml/__init__.py
touml/__main__.py
touml-0.1.4.data/scripts/touml
touml-0.1.4.dist-info/RECORD
