Metadata-Version: 2.4
Name: touml
Version: 0.1.4
Classifier: Programming Language :: Rust
Classifier: Programming Language :: Python :: Implementation :: CPython
Classifier: Programming Language :: Python :: Implementation :: PyPy
License-File: LICENSE
Summary: CLI that creates a UML class diagram from classes in a Python module or subpackage.
Keywords: rust,pyo3,rustpython,cli
Author: Rahul D. Ghosal <rdghosal@proton.me>
Author-email: "Rahul D. Ghosal" <rdghosal@proton.me>
Maintainer-email: "Rahul D. Ghosal" <rdghosal@proton.me>
License: MIT License
Requires-Python: >=3.8
Project-URL: repository, https://github.com/rdghosal/touml
